pykomodo/__init__.py
pykomodo/command_line.py
pykomodo/config.py
pykomodo/core.py
pykomodo/enhanced_chunker.py
pykomodo/multi_dirs_chunker.py
pykomodo/pykomodo_config.py
pykomodo/token_chunker.py
pykomodo-0.1.5.dist-info/licenses/NOTICE
pykomodo-0.1.5.dist-info/METADATA
pykomodo-0.1.5.dist-info/WHEEL
pykomodo-0.1.5.dist-info/entry_points.txt
pykomodo-0.1.5.dist-info/top_level.txt
pykomodo-0.1.5.dist-info/RECORD
