Metadata-Version: 2.4
Name: pykomodo
Version: 0.1.5
Summary: A Python-based parallel file chunking system for large codebases
Author: oha
License-File: NOTICE
Requires-Dist: pathspec
Requires-Dist: PyMuPDF
Requires-Dist: tiktoken
Dynamic: license-file
